sumo_tasks_pipeline/__init__.py
sumo_tasks_pipeline/commons/__init__.py
sumo_tasks_pipeline/commons/result_module.py
sumo_tasks_pipeline/commons/sumo_config_obj.py
sumo_tasks_pipeline/config_generation_module.py
sumo_tasks_pipeline/file_handler/__init__.py
sumo_tasks_pipeline/file_handler/base.py
sumo_tasks_pipeline/file_handler/gcs_filehandler.py
sumo_tasks_pipeline/file_handler/local_filehandler.py
sumo_tasks_pipeline/logger_unit.py
sumo_tasks_pipeline/operation_module/__init__.py
sumo_tasks_pipeline/operation_module/base_operation.py
sumo_tasks_pipeline/operation_module/docker_operation_module.py
sumo_tasks_pipeline/operation_module/local_operation_module.py
sumo_tasks_pipeline/pipeline/__init__.py
sumo_tasks_pipeline/pipeline/pipeline.py
sumo_tasks_pipeline/static.py
sumo_tasks_pipeline-4.0.dist-info/LICENSE.txt
sumo_tasks_pipeline-4.0.dist-info/WHEEL
sumo_tasks_pipeline-4.0.dist-info/METADATA
sumo_tasks_pipeline-4.0.dist-info/RECORD
