Metadata-Version: 2.1
Name: sumo-tasks-pipeline
Version: 4.0
Summary: Simple Python interface for a traffic simulator: SUMO
Home-page: https://github.com/Kensuke-Mitsuzawa/sumo_docker_pipeline
License: MIT
Author: Kensuke Mitsuzawa
Author-email: kensuke.mit@gmail.com
Maintainer: Kensuke Mitsuzawa
Maintainer-email: kensuke.mit@gmail.com
Requires-Python: >=3.7,<4.0
Classifier: License :: OSI Approved :: MIT License
Classifier: Programming Language :: Python :: 3
Classifier: Programming Language :: Python :: 3.7
Classifier: Programming Language :: Python :: 3.8
Classifier: Programming Language :: Python :: 3.9
Provides-Extra: full
Requires-Dist: Cartopy (>=0.18.0,<0.19.0)
Requires-Dist: Shapely (>=1.7.0,<2.0.0); extra == "full"
Requires-Dist: SumoNetVis (>=1.6.0,<2.0.0); extra == "full"
Requires-Dist: bs4
Requires-Dist: docker
Requires-Dist: geopandas (>=0.10.0,<0.11.0); extra == "full"
Requires-Dist: geoviews (>=1.9.1,<2.0.0); extra == "full"
Requires-Dist: google-cloud-storage
Requires-Dist: joblib
Requires-Dist: lxml
Requires-Dist: pandas
Requires-Dist: pyproj (>=3.0.0,<4.0.0); extra == "full"
Project-URL: Repository, https://github.com/Kensuke-Mitsuzawa/sumo_docker_pipeline
